soundcheck/__init__.py
soundcheck/cli.py
soundcheck-0.0.2.dist-info/METADATA
soundcheck-0.0.2.dist-info/WHEEL
soundcheck-0.0.2.dist-info/entry_points.txt
soundcheck-0.0.2.dist-info/licenses/LICENSE
soundcheck-0.0.2.dist-info/RECORD
