Metadata-Version: 2.3
Name: soundcheck
Version: 0.0.2
Summary: A multi-processing audio check
Project-URL: Homepage, https://github.com/seanghay/soundcheck
Project-URL: Repository, https://github.com/seanghay/soundcheck
Author-email: Seanghay Yath <seanghay.dev@gmail.com>
License: MIT License
License-File: LICENSE
Classifier: Development Status :: 4 - Beta
Classifier: Intended Audience :: Developers
Classifier: License :: OSI Approved :: MIT License
Classifier: Programming Language :: Python :: 3.8
Classifier: Topic :: Scientific/Engineering :: Artificial Intelligence
Requires-Dist: audioread
Requires-Dist: click
Requires-Dist: format-duration
Requires-Dist: prettytable
Requires-Dist: tqdm
